README.md
setup.py
kinalite/__init__.py
kinalite/__version__.py
kinalite/experiment.py
kinalite/kinetic_analysis.py
kinalite/plots.py
kinalite.egg-info/PKG-INFO
kinalite.egg-info/SOURCES.txt
kinalite.egg-info/dependency_links.txt
kinalite.egg-info/requires.txt
kinalite.egg-info/top_level.txt