Metadata-Version: 2.1
Name: kinalite
Version: 0.0.6
Summary: A simple package for VTNA analysis of chemical reactions
Home-page: https://gitlab.com/heingroup/kinalite
Author: Sean Clark
Author-email: sean@v13inc.com
License: MIT
Platform: UNKNOWN
Requires-Python: >=3.6.0
